KubernetesZhongwenZhinanYunYuanshengYingyongJiagouShijianShouce/README.md
KubernetesZhongwenZhinanYunYuanshengYingyongJiagouShijianShouce/__init__.py
KubernetesZhongwenZhinanYunYuanshengYingyongJiagouShijianShouce/__main__.py
KubernetesZhongwenZhinanYunYuanshengYingyongJiagouShijianShouce/file.epub
KubernetesZhongwenZhinanYunYuanshengYingyongJiagouShijianShouce/index.html
KubernetesZhongwenZhinanYunYuanshengYingyongJiagouShijianShouce/css/__init__.py
KubernetesZhongwenZhinanYunYuanshengYingyongJiagouShijianShouce/css/annotations.css
KubernetesZhongwenZhinanYunYuanshengYingyongJiagouShijianShouce/css/main.css
KubernetesZhongwenZhinanYunYuanshengYingyongJiagouShijianShouce/css/normalize.css
KubernetesZhongwenZhinanYunYuanshengYingyongJiagouShijianShouce/css/popup.css
KubernetesZhongwenZhinanYunYuanshengYingyongJiagouShijianShouce/font/__init__.py
KubernetesZhongwenZhinanYunYuanshengYingyongJiagouShijianShouce/font/fontello.eot
KubernetesZhongwenZhinanYunYuanshengYingyongJiagouShijianShouce/font/fontello.svg
KubernetesZhongwenZhinanYunYuanshengYingyongJiagouShijianShouce/font/fontello.ttf
KubernetesZhongwenZhinanYunYuanshengYingyongJiagouShijianShouce/font/fontello.woff
KubernetesZhongwenZhinanYunYuanshengYingyongJiagouShijianShouce/img/__init__.py
KubernetesZhongwenZhinanYunYuanshengYingyongJiagouShijianShouce/img/annotator-glyph-sprite.png
KubernetesZhongwenZhinanYunYuanshengYingyongJiagouShijianShouce/img/annotator-icon-sprite.png
KubernetesZhongwenZhinanYunYuanshengYingyongJiagouShijianShouce/img/apple-touch-icon.png
KubernetesZhongwenZhinanYunYuanshengYingyongJiagouShijianShouce/img/cancelfullscreen.png
KubernetesZhongwenZhinanYunYuanshengYingyongJiagouShijianShouce/img/close.png
KubernetesZhongwenZhinanYunYuanshengYingyongJiagouShijianShouce/img/fullscreen.png
KubernetesZhongwenZhinanYunYuanshengYingyongJiagouShijianShouce/img/loader.gif
KubernetesZhongwenZhinanYunYuanshengYingyongJiagouShijianShouce/img/menu-icon.png
kubernetes_zhongwen_zhinan_yun_yuansheng_yingyong_jiagou_shijian_shouce-2024.3.6.0.dist-info/METADATA
kubernetes_zhongwen_zhinan_yun_yuansheng_yingyong_jiagou_shijian_shouce-2024.3.6.0.dist-info/WHEEL
kubernetes_zhongwen_zhinan_yun_yuansheng_yingyong_jiagou_shijian_shouce-2024.3.6.0.dist-info/entry_points.txt
kubernetes_zhongwen_zhinan_yun_yuansheng_yingyong_jiagou_shijian_shouce-2024.3.6.0.dist-info/top_level.txt
kubernetes_zhongwen_zhinan_yun_yuansheng_yingyong_jiagou_shijian_shouce-2024.3.6.0.dist-info/RECORD
